lmhw/__init__.py
lmhw-2025.9.1.dist-info/METADATA
lmhw-2025.9.1.dist-info/WHEEL
lmhw-2025.9.1.dist-info/RECORD
