Metadata-Version: 2.3
Name: lmhw
Version: 2025.9.1
Summary: Lagrangian marine heatwaves
License: MIT
Author: Ezra Eisbrenner
Author-email: lmhw@ezra-eisbrenner.eu
Requires-Python: <3.13,>=3.9
Classifier: License :: OSI Approved :: MIT License
Classifier: Programming Language :: Python :: 3
Classifier: Programming Language :: Python :: 3.9
Classifier: Programming Language :: Python :: 3.10
Classifier: Programming Language :: Python :: 3.11
Classifier: Programming Language :: Python :: 3.12
